curtains/__init__.py
curtains/basic_auth.py
curtains/ip_networks.py
curtains/middleware.py
curtains/only_staff.py
django_curtains-0.7.0.dist-info/METADATA
django_curtains-0.7.0.dist-info/WHEEL
django_curtains-0.7.0.dist-info/licenses/LICENSE
django_curtains-0.7.0.dist-info/RECORD
